CHANGES.txt
LICENSE
MANIFEST.in
README.rst
setup.cfg
setup.py
onvif/__init__.py
onvif/cli.py
onvif/client.py
onvif/definition.py
onvif/exceptions.py
onvif/version.txt
onvif_zeep_roboticia.egg-info/PKG-INFO
onvif_zeep_roboticia.egg-info/SOURCES.txt
onvif_zeep_roboticia.egg-info/dependency_links.txt
onvif_zeep_roboticia.egg-info/entry_points.txt
onvif_zeep_roboticia.egg-info/not-zip-safe
onvif_zeep_roboticia.egg-info/requires.txt
onvif_zeep_roboticia.egg-info/top_level.txt
wsdl/accesscontrol.wsdl
wsdl/actionengine.wsdl
wsdl/addressing
wsdl/advancedsecurity.wsdl
wsdl/analytics.wsdl
wsdl/analyticsdevice.wsdl
wsdl/b-2.xsd
wsdl/bf-2.xsd
wsdl/bw-2.wsdl
wsdl/deviceio.wsdl
wsdl/devicemgmt.wsdl
wsdl/display.wsdl
wsdl/doorcontrol.wsdl
wsdl/envelope
wsdl/events.wsdl
wsdl/imaging.wsdl
wsdl/include
wsdl/media.wsdl
wsdl/onvif.xsd
wsdl/ptz.wsdl
wsdl/r-2.xsd
wsdl/receiver.wsdl
wsdl/recording.wsdl
wsdl/remotediscovery.wsdl
wsdl/replay.wsdl
wsdl/rw-2.wsdl
wsdl/search.wsdl
wsdl/t-1.xsd
wsdl/types.xsd
wsdl/ws-addr.xsd
wsdl/ws-discovery.xsd
wsdl/xml.xsd
wsdl/xmlmime